trixyscope/__init__.py
trixyscope/__main__.py
trixyscope/logger.py
trixyscope/scratch_session_config.py
trixyscope/session.py
trixyscope/calibration/charuco.py
trixyscope/calibration/corner_tracker.py
trixyscope/calibration/draw_charuco.py
trixyscope/calibration/monocalibrator.py
trixyscope/calibration/omnicalibrator.py
trixyscope/calibration/capture_volume/capture_volume.py
trixyscope/calibration/capture_volume/capture_volume_stage_1.pkl
trixyscope/calibration/capture_volume/point_estimates.py
trixyscope/calibration/capture_volume/quality_controller.py
trixyscope/calibration/capture_volume/seaborn_summaries.py
trixyscope/calibration/capture_volume/helper_functions/get_point_estimates.py
trixyscope/calibration/capture_volume/helper_functions/get_stereotriangulated_table.py
trixyscope/cameras/camera.py
trixyscope/cameras/camera_array.py
trixyscope/cameras/camera_array_builder.py
trixyscope/cameras/data_packets.py
trixyscope/cameras/live_stream.py
trixyscope/cameras/pyav_sandbox.py
trixyscope/cameras/synchronizer.py
trixyscope/gui/main.py
trixyscope/gui/qt_logger.py
trixyscope/gui/widgets.py
trixyscope/gui/wizard_charuco.py
trixyscope/gui/wizard_directory.py
trixyscope/gui/camera_config/camera_config_dialogue.py
trixyscope/gui/camera_config/camera_config_dialogue_old.py
trixyscope/gui/camera_config/camera_tabs.py
trixyscope/gui/camera_config/frame_emitter.py
trixyscope/gui/icons/orb.svg
trixyscope/gui/icons/rotate-camera-left.svg
trixyscope/gui/icons/rotate-camera-right.svg
trixyscope/gui/icons/rotate_right.svg
trixyscope/gui/omniframe/omni_frame_builder.py
trixyscope/gui/omniframe/omni_frame_widget.py
trixyscope/gui/vizualize/camera_mesh.py
trixyscope/gui/vizualize/capture_volume_dialog.py
trixyscope/gui/vizualize/capture_volume_visualizer.py
trixyscope/recording/recorded_stream.py
trixyscope/recording/undistort_video.py
trixyscope/recording/video_recorder.py
trixyscope/triangulate/stereo_points_builder.py
trixyscope/triangulate/triangulator.py
trixyscope-0.0.0.dist-info/entry_points.txt
trixyscope-0.0.0.dist-info/LICENSE.md
trixyscope-0.0.0.dist-info/WHEEL
trixyscope-0.0.0.dist-info/METADATA
trixyscope-0.0.0.dist-info/RECORD
